tappay/__init__.py
tappay-0.4.0.dist-info/METADATA
tappay-0.4.0.dist-info/RECORD
tappay-0.4.0.dist-info/WHEEL
tappay-0.4.0.dist-info/top_level.txt
