Metadata-Version: 2.1
Name: tappay
Version: 0.4.0
Summary: TapPay Client Library for Python
Home-page: http://github.com/shihweilo/tappay-python
Author: Shih Wei Chris Lo
Author-email: shihwei@gmail.com
License: MIT
Platform: any
Classifier: Programming Language :: Python
Classifier: Programming Language :: Python :: 2
Classifier: Programming Language :: Python :: 2.7
Classifier: Programming Language :: Python :: 3
Classifier: Programming Language :: Python :: 3.3
Classifier: Programming Language :: Python :: 3.4
Classifier: Programming Language :: Python :: 3.5
Classifier: Programming Language :: Python :: 3.6
Classifier: Programming Language :: Python :: 3.7
Requires-Python: >=2.7, !=3.0.*, !=3.1.*, !=3.2.*, !=3.3.*
Requires-Dist: requests (>=2.4.2)
